cut_video/__init__.py
cut_video/cut_video.py
llm_jhy-0.0.1.data/data/cut_video/to_erase.json
llm_jhy-0.0.1.data/scripts/cut_video.py
llm_jhy-0.0.1.dist-info/LICENCE
llm_jhy-0.0.1.dist-info/METADATA
llm_jhy-0.0.1.dist-info/WHEEL
llm_jhy-0.0.1.dist-info/entry_points.txt
llm_jhy-0.0.1.dist-info/top_level.txt
llm_jhy-0.0.1.dist-info/RECORD
