Metadata-Version: 2.1
Name: llm-jhy
Version: 0.0.1
Summary: Easily cut the video by moviepy
Home-page: https://github.com/chunleili/cut_video
Author: jhy
Author-email: 2538134102@qq.com
License: MIT
Keywords: python,moviepy,cut video
Classifier: Development Status :: 3 - Alpha
Classifier: Intended Audience :: Developers
Classifier: Programming Language :: Python :: 3
Classifier: Operating System :: Microsoft :: Windows
License-File: LICENCE
Requires-Dist: moviepy
